{
  "generated_at": "2026-04-04T20:45:49Z",
  "n_files_scanned": 42,
  "per_contract": {
    "bitcoin_daily": {
      "n_predictions": 42,
      "history": [
        {
          "timestamp": "2026-04-04T05:28:17Z",
          "tier": "sonnet",
          "type": "binary",
          "prediction": 0.57,
          "market_price": 0.565,
          "signed_error": 0.0050000000000000044
        },
        {
          "timestamp": "2026-04-04T08:54:43Z",
          "tier": "haiku",
          "type": "binary",
          "prediction": 0.66,
          "market_price": 0.685,
          "signed_error": -0.025000000000000022
        },
        {
          "timestamp": "2026-04-04T13:12:20Z",
          "tier": "haiku",
          "type": "binary",
          "prediction": 0.86,
          "market_price": 0.845,
          "signed_error": 0.015000000000000013
        },
        {
          "timestamp": "2026-04-04T16:47:13Z",
          "tier": "haiku",
          "type": "binary",
          "prediction": 0.99,
          "market_price": 0.9995,
          "signed_error": -0.009500000000000064
        },
        {
          "timestamp": "2026-04-04T20:44:03Z",
          "tier": "haiku",
          "type": "binary",
          "prediction": 0.99,
          "market_price": 1.0,
          "signed_error": -0.010000000000000009
        }
      ],
      "avg_signed_error": 0.004,
      "avg_abs_error": 0.05,
      "bias": "neutral"
    },
    "nyc_temp": {
      "n_predictions": 42,
      "history": [
        {
          "timestamp": "2026-04-04T05:28:17Z",
          "tier": "opus",
          "type": "multi-outcome",
          "avg_outcome_div": 0.005590909090909099,
          "max_outcome_div": 0.02950000000000008,
          "n_outcomes": 11
        },
        {
          "timestamp": "2026-04-04T08:54:43Z",
          "tier": "haiku",
          "type": "multi-outcome",
          "avg_outcome_div": 0.005454545454545463,
          "max_outcome_div": 0.02950000000000008,
          "n_outcomes": 11
        },
        {
          "timestamp": "2026-04-04T13:12:20Z",
          "tier": "opus",
          "type": "multi-outcome",
          "avg_outcome_div": 0.0036363636363636385,
          "max_outcome_div": 0.020000000000000018,
          "n_outcomes": 11
        },
        {
          "timestamp": "2026-04-04T16:47:13Z",
          "tier": "opus",
          "type": "multi-outcome",
          "avg_outcome_div": 0.0,
          "max_outcome_div": 0.0,
          "n_outcomes": 11
        },
        {
          "timestamp": "2026-04-04T20:44:03Z",
          "tier": "opus",
          "type": "multi-outcome",
          "avg_outcome_div": 0.009090909090909094,
          "max_outcome_div": 0.050000000000000044,
          "n_outcomes": 11
        }
      ],
      "avg_multi_div": 0.015
    },
    "miami_temp": {
      "n_predictions": 36,
      "history": [
        {
          "timestamp": "2026-04-04T05:28:17Z",
          "tier": "opus",
          "type": "multi-outcome",
          "avg_outcome_div": 0.10222727272727271,
          "max_outcome_div": 0.32499999999999996,
          "n_outcomes": 11
        },
        {
          "timestamp": "2026-04-04T08:54:43Z",
          "tier": "opus",
          "type": "multi-outcome",
          "avg_outcome_div": 0.10381818181818181,
          "max_outcome_div": 0.32649999999999996,
          "n_outcomes": 11
        },
        {
          "timestamp": "2026-04-04T13:12:20Z",
          "tier": "opus",
          "type": "multi-outcome",
          "avg_outcome_div": 0.025727272727272734,
          "max_outcome_div": 0.08849999999999998,
          "n_outcomes": 11
        },
        {
          "timestamp": "2026-04-04T16:47:13Z",
          "tier": "opus",
          "type": "multi-outcome",
          "avg_outcome_div": 0.01554545454545454,
          "max_outcome_div": 0.05499999999999994,
          "n_outcomes": 11
        },
        {
          "timestamp": "2026-04-04T20:44:03Z",
          "tier": "opus",
          "type": "multi-outcome",
          "avg_outcome_div": 0.004454545454545462,
          "max_outcome_div": 0.02950000000000008,
          "n_outcomes": 11
        }
      ],
      "avg_multi_div": 0.036
    },
    "us-iran-nuclear-deal-before-2027": {
      "n_predictions": 14,
      "history": [
        {
          "timestamp": "2026-04-02T13:34:20Z",
          "tier": "sonnet",
          "type": "binary",
          "prediction": 0.41,
          "market_price": 0.385,
          "signed_error": 0.024999999999999967
        },
        {
          "timestamp": "2026-04-03T02:55:31Z",
          "tier": "haiku",
          "type": "binary",
          "prediction": 0.43,
          "market_price": 0.385,
          "signed_error": 0.044999999999999984
        },
        {
          "timestamp": "2026-04-03T13:20:11Z",
          "tier": "haiku",
          "type": "binary",
          "prediction": 0.42,
          "market_price": 0.39,
          "signed_error": 0.02999999999999997
        },
        {
          "timestamp": "2026-04-04T02:44:25Z",
          "tier": "haiku",
          "type": "binary",
          "prediction": 0.42,
          "market_price": 0.385,
          "signed_error": 0.034999999999999976
        },
        {
          "timestamp": "2026-04-04T13:12:20Z",
          "tier": "haiku",
          "type": "binary",
          "prediction": 0.38,
          "market_price": 0.385,
          "signed_error": -0.0050000000000000044
        }
      ],
      "avg_signed_error": -0.015,
      "avg_abs_error": 0.05,
      "bias": "neutral"
    },
    "us-iran-nuclear-deal-by-april-30": {
      "n_predictions": 14,
      "history": [
        {
          "timestamp": "2026-04-02T13:34:20Z",
          "tier": "haiku",
          "type": "binary",
          "prediction": 0.03,
          "market_price": 0.045,
          "signed_error": -0.015
        },
        {
          "timestamp": "2026-04-03T02:55:31Z",
          "tier": "haiku",
          "type": "binary",
          "prediction": 0.03,
          "market_price": 0.0325,
          "signed_error": -0.0025000000000000022
        },
        {
          "timestamp": "2026-04-03T13:20:11Z",
          "tier": "haiku",
          "type": "binary",
          "prediction": 0.04,
          "market_price": 0.031,
          "signed_error": 0.009000000000000001
        },
        {
          "timestamp": "2026-04-04T02:44:25Z",
          "tier": "haiku",
          "type": "binary",
          "prediction": 0.05,
          "market_price": 0.0335,
          "signed_error": 0.0165
        },
        {
          "timestamp": "2026-04-04T13:12:20Z",
          "tier": "haiku",
          "type": "binary",
          "prediction": 0.04,
          "market_price": 0.031,
          "signed_error": 0.009000000000000001
        }
      ],
      "avg_signed_error": -0.01,
      "avg_abs_error": 0.023,
      "bias": "neutral"
    },
    "strait-of-hormuz-traffic-returns-to-normal-by-april-30": {
      "n_predictions": 14,
      "history": [
        {
          "timestamp": "2026-04-02T13:34:20Z",
          "tier": "haiku",
          "type": "binary",
          "prediction": 0.12,
          "market_price": 0.135,
          "signed_error": -0.015000000000000013
        },
        {
          "timestamp": "2026-04-03T02:55:31Z",
          "tier": "haiku",
          "type": "binary",
          "prediction": 0.09,
          "market_price": 0.115,
          "signed_error": -0.02500000000000001
        },
        {
          "timestamp": "2026-04-03T13:20:11Z",
          "tier": "haiku",
          "type": "binary",
          "prediction": 0.06,
          "market_price": 0.095,
          "signed_error": -0.035
        },
        {
          "timestamp": "2026-04-04T02:44:25Z",
          "tier": "haiku",
          "type": "binary",
          "prediction": 0.08,
          "market_price": 0.115,
          "signed_error": -0.035
        },
        {
          "timestamp": "2026-04-04T13:12:20Z",
          "tier": "haiku",
          "type": "binary",
          "prediction": 0.07,
          "market_price": 0.095,
          "signed_error": -0.024999999999999994
        }
      ],
      "avg_signed_error": -0.014,
      "avg_abs_error": 0.026,
      "bias": "neutral"
    },
    "will-iran-close-the-strait-of-hormuz-by-2027": {
      "n_predictions": 14,
      "history": [
        {
          "timestamp": "2026-04-02T13:34:20Z",
          "tier": "opus",
          "type": "multi-outcome",
          "avg_outcome_div": 0.43225806451612897,
          "max_outcome_div": 0.8709677419354839,
          "n_outcomes": 6
        },
        {
          "timestamp": "2026-04-03T02:55:31Z",
          "tier": "opus",
          "type": "multi-outcome",
          "avg_outcome_div": 0.5042735042735043,
          "max_outcome_div": 0.8205128205128205,
          "n_outcomes": 6
        },
        {
          "timestamp": "2026-04-03T13:20:11Z",
          "tier": "opus",
          "type": "multi-outcome",
          "avg_outcome_div": 0.5133333333333333,
          "max_outcome_div": 0.8400000000000001,
          "n_outcomes": 6
        },
        {
          "timestamp": "2026-04-04T02:44:25Z",
          "tier": "opus",
          "type": "multi-outcome",
          "avg_outcome_div": 0.4791666666666667,
          "max_outcome_div": 0.75,
          "n_outcomes": 6
        },
        {
          "timestamp": "2026-04-04T13:12:20Z",
          "tier": "opus",
          "type": "multi-outcome",
          "avg_outcome_div": 0.4791666666666667,
          "max_outcome_div": 0.75,
          "n_outcomes": 6
        }
      ],
      "avg_multi_div": 0.493
    },
    "next-leader-out-of-power-before-2027-795": {
      "n_predictions": 14,
      "history": [
        {
          "timestamp": "2026-04-02T13:34:20Z",
          "tier": "haiku",
          "type": "multi-outcome",
          "avg_outcome_div": 0.008366666666666666,
          "max_outcome_div": 0.041499999999999995,
          "n_outcomes": 15
        },
        {
          "timestamp": "2026-04-03T02:55:31Z",
          "tier": "haiku",
          "type": "multi-outcome",
          "avg_outcome_div": 0.00950350877192984,
          "max_outcome_div": 0.04578947368421055,
          "n_outcomes": 15
        },
        {
          "timestamp": "2026-04-03T13:20:11Z",
          "tier": "sonnet",
          "type": "multi-outcome",
          "avg_outcome_div": 0.010805522288755821,
          "max_outcome_div": 0.07115768463073857,
          "n_outcomes": 15
        },
        {
          "timestamp": "2026-04-04T02:44:25Z",
          "tier": "sonnet",
          "type": "multi-outcome",
          "avg_outcome_div": 0.00521862045531771,
          "max_outcome_div": 0.0237665647298676,
          "n_outcomes": 15
        },
        {
          "timestamp": "2026-04-04T13:12:20Z",
          "tier": "sonnet",
          "type": "multi-outcome",
          "avg_outcome_div": 0.007012820512820522,
          "max_outcome_div": 0.02512820512820524,
          "n_outcomes": 15
        }
      ],
      "avg_multi_div": 0.011
    },
    "save-act-signed-into-law-in-2026": {
      "n_predictions": 14,
      "history": [
        {
          "timestamp": "2026-04-02T13:34:20Z",
          "tier": "haiku",
          "type": "binary",
          "prediction": 0.12,
          "market_price": 0.135,
          "signed_error": -0.015000000000000013
        },
        {
          "timestamp": "2026-04-03T02:55:31Z",
          "tier": "haiku",
          "type": "binary",
          "prediction": 0.1,
          "market_price": 0.115,
          "signed_error": -0.015
        },
        {
          "timestamp": "2026-04-03T13:20:11Z",
          "tier": "haiku",
          "type": "binary",
          "prediction": 0.1,
          "market_price": 0.115,
          "signed_error": -0.015
        },
        {
          "timestamp": "2026-04-04T02:44:25Z",
          "tier": "haiku",
          "type": "binary",
          "prediction": 0.09,
          "market_price": 0.105,
          "signed_error": -0.015
        },
        {
          "timestamp": "2026-04-04T13:12:20Z",
          "tier": "haiku",
          "type": "binary",
          "prediction": 0.1,
          "market_price": 0.105,
          "signed_error": -0.0049999999999999906
        }
      ],
      "avg_signed_error": -0.003,
      "avg_abs_error": 0.016,
      "bias": "neutral"
    },
    "us-recession-by-end-of-2026": {
      "n_predictions": 14,
      "history": [
        {
          "timestamp": "2026-04-02T13:34:20Z",
          "tier": "haiku",
          "type": "binary",
          "prediction": 0.32,
          "market_price": 0.315,
          "signed_error": 0.0050000000000000044
        },
        {
          "timestamp": "2026-04-03T02:55:31Z",
          "tier": "haiku",
          "type": "binary",
          "prediction": 0.32,
          "market_price": 0.315,
          "signed_error": 0.0050000000000000044
        },
        {
          "timestamp": "2026-04-03T13:20:11Z",
          "tier": "haiku",
          "type": "binary",
          "prediction": 0.28,
          "market_price": 0.275,
          "signed_error": 0.0050000000000000044
        },
        {
          "timestamp": "2026-04-04T02:44:25Z",
          "tier": "haiku",
          "type": "binary",
          "prediction": 0.33,
          "market_price": 0.315,
          "signed_error": 0.015000000000000013
        },
        {
          "timestamp": "2026-04-04T13:12:20Z",
          "tier": "haiku",
          "type": "binary",
          "prediction": 0.32,
          "market_price": 0.315,
          "signed_error": 0.0050000000000000044
        }
      ],
      "avg_signed_error": -0.003,
      "avg_abs_error": 0.02,
      "bias": "neutral"
    },
    "fed-decision-in-april": {
      "n_predictions": 14,
      "history": [
        {
          "timestamp": "2026-04-02T13:34:20Z",
          "tier": "haiku",
          "type": "multi-outcome",
          "avg_outcome_div": 0.0038750000000000156,
          "max_outcome_div": 0.007500000000000062,
          "n_outcomes": 4
        },
        {
          "timestamp": "2026-04-03T02:55:31Z",
          "tier": "haiku",
          "type": "multi-outcome",
          "avg_outcome_div": 0.014500000000000022,
          "max_outcome_div": 0.02950000000000008,
          "n_outcomes": 4
        },
        {
          "timestamp": "2026-04-03T13:20:11Z",
          "tier": "sonnet",
          "type": "multi-outcome",
          "avg_outcome_div": 0.008250000000000018,
          "max_outcome_div": 0.01750000000000007,
          "n_outcomes": 4
        },
        {
          "timestamp": "2026-04-04T02:44:25Z",
          "tier": "haiku",
          "type": "multi-outcome",
          "avg_outcome_div": 0.0037500000000000146,
          "max_outcome_div": 0.0075,
          "n_outcomes": 4
        },
        {
          "timestamp": "2026-04-04T13:12:20Z",
          "tier": "haiku",
          "type": "multi-outcome",
          "avg_outcome_div": 0.006500000000000017,
          "max_outcome_div": 0.013500000000000068,
          "n_outcomes": 4
        }
      ],
      "avg_multi_div": 0.007
    },
    "march-inflation-us-annual": {
      "n_predictions": 14,
      "history": [
        {
          "timestamp": "2026-04-02T13:34:20Z",
          "tier": "sonnet",
          "type": "multi-outcome",
          "avg_outcome_div": 0.022666666666666672,
          "max_outcome_div": 0.09950000000000003,
          "n_outcomes": 9
        },
        {
          "timestamp": "2026-04-03T02:55:31Z",
          "tier": "sonnet",
          "type": "multi-outcome",
          "avg_outcome_div": 0.008166666666666676,
          "max_outcome_div": 0.034500000000000086,
          "n_outcomes": 9
        },
        {
          "timestamp": "2026-04-03T13:20:11Z",
          "tier": "sonnet",
          "type": "multi-outcome",
          "avg_outcome_div": 0.006500000000000008,
          "max_outcome_div": 0.0275,
          "n_outcomes": 9
        },
        {
          "timestamp": "2026-04-04T02:44:25Z",
          "tier": "haiku",
          "type": "multi-outcome",
          "avg_outcome_div": 0.003555555555555557,
          "max_outcome_div": 0.014000000000000012,
          "n_outcomes": 9
        },
        {
          "timestamp": "2026-04-04T13:12:20Z",
          "tier": "sonnet",
          "type": "multi-outcome",
          "avg_outcome_div": 0.014222222222222216,
          "max_outcome_div": 0.06799999999999995,
          "n_outcomes": 9
        }
      ],
      "avg_multi_div": 0.024
    },
    "what-price-will-bitcoin-hit-before-2027": {
      "n_predictions": 14,
      "history": [
        {
          "timestamp": "2026-04-02T13:34:20Z",
          "tier": "opus",
          "type": "multi-outcome",
          "avg_outcome_div": 0.65,
          "max_outcome_div": 0.9265975820379966,
          "n_outcomes": 15
        },
        {
          "timestamp": "2026-04-03T02:55:31Z",
          "tier": "opus",
          "type": "multi-outcome",
          "avg_outcome_div": 0.6503333333333333,
          "max_outcome_div": 0.9260869565217391,
          "n_outcomes": 15
        },
        {
          "timestamp": "2026-04-03T13:20:11Z",
          "tier": "opus",
          "type": "multi-outcome",
          "avg_outcome_div": 0.6513333333333334,
          "max_outcome_div": 0.9319419237749547,
          "n_outcomes": 15
        },
        {
          "timestamp": "2026-04-04T02:44:25Z",
          "tier": "opus",
          "type": "multi-outcome",
          "avg_outcome_div": 0.6506666666666666,
          "max_outcome_div": 0.9295774647887324,
          "n_outcomes": 15
        },
        {
          "timestamp": "2026-04-04T13:12:20Z",
          "tier": "opus",
          "type": "multi-outcome",
          "avg_outcome_div": 0.6526666666666666,
          "max_outcome_div": 0.9481865284974094,
          "n_outcomes": 15
        }
      ],
      "avg_multi_div": 0.656
    },
    "jerome-powell-out-as-fed-chair-by": {
      "n_predictions": 14,
      "history": [
        {
          "timestamp": "2026-04-02T13:34:20Z",
          "tier": "opus",
          "type": "multi-outcome",
          "avg_outcome_div": 0.49225,
          "max_outcome_div": 0.7769736842105264,
          "n_outcomes": 2
        },
        {
          "timestamp": "2026-04-03T02:55:31Z",
          "tier": "opus",
          "type": "multi-outcome",
          "avg_outcome_div": 0.7925,
          "max_outcome_div": 0.797,
          "n_outcomes": 2
        },
        {
          "timestamp": "2026-04-03T13:20:11Z",
          "tier": "opus",
          "type": "multi-outcome",
          "avg_outcome_div": 0.49475,
          "max_outcome_div": 0.9865,
          "n_outcomes": 2
        },
        {
          "timestamp": "2026-04-04T02:44:25Z",
          "tier": "opus",
          "type": "multi-outcome",
          "avg_outcome_div": 0.4945,
          "max_outcome_div": 0.986,
          "n_outcomes": 2
        },
        {
          "timestamp": "2026-04-04T13:12:20Z",
          "tier": "opus",
          "type": "multi-outcome",
          "avg_outcome_div": 0.49250000000000005,
          "max_outcome_div": 0.788,
          "n_outcomes": 2
        }
      ],
      "avg_multi_div": 0.59
    },
    "who-will-be-confirmed-as-fed-chair": {
      "n_predictions": 14,
      "history": [
        {
          "timestamp": "2026-04-02T13:34:20Z",
          "tier": "sonnet",
          "type": "multi-outcome",
          "avg_outcome_div": 0.46416666666666667,
          "max_outcome_div": 0.5,
          "n_outcomes": 15
        },
        {
          "timestamp": "2026-04-03T02:55:31Z",
          "tier": "sonnet",
          "type": "multi-outcome",
          "avg_outcome_div": 0.4644333333333334,
          "max_outcome_div": 0.49029126213592233,
          "n_outcomes": 15
        },
        {
          "timestamp": "2026-04-03T13:20:11Z",
          "tier": "sonnet",
          "type": "multi-outcome",
          "avg_outcome_div": 0.4644999999999999,
          "max_outcome_div": 0.49702675916749256,
          "n_outcomes": 15
        },
        {
          "timestamp": "2026-04-04T02:44:25Z",
          "tier": "sonnet",
          "type": "multi-outcome",
          "avg_outcome_div": 0.46436666666666676,
          "max_outcome_div": 0.5132386934673367,
          "n_outcomes": 15
        },
        {
          "timestamp": "2026-04-04T13:12:20Z",
          "tier": "sonnet",
          "type": "multi-outcome",
          "avg_outcome_div": 0.4643000000000001,
          "max_outcome_div": 0.49,
          "n_outcomes": 15
        }
      ],
      "avg_multi_div": 0.464
    },
    "which-party-will-win-the-house-in-2026": {
      "n_predictions": 14,
      "history": [
        {
          "timestamp": "2026-04-02T13:34:20Z",
          "tier": "opus",
          "type": "multi-outcome",
          "avg_outcome_div": 0.3888888888888889,
          "max_outcome_div": 0.5,
          "n_outcomes": 9
        },
        {
          "timestamp": "2026-04-03T02:55:31Z",
          "tier": "sonnet",
          "type": "multi-outcome",
          "avg_outcome_div": 0.4122222222222222,
          "max_outcome_div": 0.5,
          "n_outcomes": 9
        },
        {
          "timestamp": "2026-04-03T13:20:11Z",
          "tier": "sonnet",
          "type": "multi-outcome",
          "avg_outcome_div": 0.42333333333333334,
          "max_outcome_div": 0.5,
          "n_outcomes": 9
        },
        {
          "timestamp": "2026-04-04T02:44:25Z",
          "tier": "sonnet",
          "type": "multi-outcome",
          "avg_outcome_div": 0.3966666666666667,
          "max_outcome_div": 0.5,
          "n_outcomes": 9
        },
        {
          "timestamp": "2026-04-04T13:12:20Z",
          "tier": "sonnet",
          "type": "multi-outcome",
          "avg_outcome_div": 0.40555555555555556,
          "max_outcome_div": 0.5,
          "n_outcomes": 9
        }
      ],
      "avg_multi_div": 0.418
    },
    "balance-of-power-2026-midterms": {
      "n_predictions": 14,
      "history": [
        {
          "timestamp": "2026-04-02T13:34:20Z",
          "tier": "sonnet",
          "type": "multi-outcome",
          "avg_outcome_div": 0.058299999999999984,
          "max_outcome_div": 0.07500000000000001,
          "n_outcomes": 5
        },
        {
          "timestamp": "2026-04-03T02:55:31Z",
          "tier": "sonnet",
          "type": "multi-outcome",
          "avg_outcome_div": 0.0509,
          "max_outcome_div": 0.125,
          "n_outcomes": 5
        },
        {
          "timestamp": "2026-04-03T13:20:11Z",
          "tier": "sonnet",
          "type": "multi-outcome",
          "avg_outcome_div": 0.0431,
          "max_outcome_div": 0.10499999999999998,
          "n_outcomes": 5
        },
        {
          "timestamp": "2026-04-04T02:44:25Z",
          "tier": "sonnet",
          "type": "multi-outcome",
          "avg_outcome_div": 0.06489999999999999,
          "max_outcome_div": 0.10499999999999998,
          "n_outcomes": 5
        },
        {
          "timestamp": "2026-04-04T13:12:20Z",
          "tier": "sonnet",
          "type": "multi-outcome",
          "avg_outcome_div": 0.077,
          "max_outcome_div": 0.10499999999999998,
          "n_outcomes": 5
        }
      ],
      "avg_multi_div": 0.055
    },
    "2026-fifa-world-cup-winner-595": {
      "n_predictions": 7,
      "history": [
        {
          "timestamp": "2026-03-30T03:03:17Z",
          "tier": "sonnet",
          "type": "multi-outcome",
          "avg_outcome_div": 0.43333333333333335,
          "max_outcome_div": 0.49,
          "n_outcomes": 15
        },
        {
          "timestamp": "2026-03-31T02:54:04Z",
          "tier": "sonnet",
          "type": "multi-outcome",
          "avg_outcome_div": 0.43333333333333324,
          "max_outcome_div": 0.43499999999999994,
          "n_outcomes": 15
        },
        {
          "timestamp": "2026-04-02T02:53:10Z",
          "tier": "sonnet",
          "type": "multi-outcome",
          "avg_outcome_div": 0.22436666666666666,
          "max_outcome_div": 0.495,
          "n_outcomes": 15
        },
        {
          "timestamp": "2026-04-03T02:55:31Z",
          "tier": "sonnet",
          "type": "multi-outcome",
          "avg_outcome_div": 0.21003333333333338,
          "max_outcome_div": 0.45,
          "n_outcomes": 15
        },
        {
          "timestamp": "2026-04-04T02:44:25Z",
          "tier": "sonnet",
          "type": "multi-outcome",
          "avg_outcome_div": 0.21031558901682904,
          "max_outcome_div": 0.4512843224092117,
          "n_outcomes": 15
        }
      ],
      "avg_multi_div": 0.34
    },
    "2026-nba-champion": {
      "n_predictions": 7,
      "history": [
        {
          "timestamp": "2026-03-30T03:03:17Z",
          "tier": "haiku",
          "type": "multi-outcome",
          "avg_outcome_div": 0.005848424543946932,
          "max_outcome_div": 0.026691542288557246,
          "n_outcomes": 15
        },
        {
          "timestamp": "2026-03-31T02:54:04Z",
          "tier": "haiku",
          "type": "multi-outcome",
          "avg_outcome_div": 0.011933333333333332,
          "max_outcome_div": 0.04500000000000004,
          "n_outcomes": 15
        },
        {
          "timestamp": "2026-04-02T02:53:10Z",
          "tier": "sonnet",
          "type": "multi-outcome",
          "avg_outcome_div": 0.004804713804713806,
          "max_outcome_div": 0.019813131313131296,
          "n_outcomes": 15
        },
        {
          "timestamp": "2026-04-03T02:55:31Z",
          "tier": "sonnet",
          "type": "multi-outcome",
          "avg_outcome_div": 0.0030855043420173695,
          "max_outcome_div": 0.005540080160320636,
          "n_outcomes": 15
        },
        {
          "timestamp": "2026-04-04T02:44:25Z",
          "tier": "haiku",
          "type": "multi-outcome",
          "avg_outcome_div": 0.009120064724919096,
          "max_outcome_div": 0.0451941747572816,
          "n_outcomes": 15
        }
      ],
      "avg_multi_div": 0.006
    },
    "which-company-has-the-best-ai-model-end-of-march-751": {
      "n_predictions": 3,
      "history": [
        {
          "timestamp": "2026-03-29T01:27:58Z",
          "tier": "sonnet",
          "type": "multi-outcome",
          "avg_outcome_div": 0.4661666666666665,
          "max_outcome_div": 0.49702380952380953,
          "n_outcomes": 15
        },
        {
          "timestamp": "2026-03-29T03:02:03Z",
          "tier": "sonnet",
          "type": "multi-outcome",
          "avg_outcome_div": 0.4662666666666668,
          "max_outcome_div": 0.48648648648648646,
          "n_outcomes": 15
        },
        {
          "timestamp": "2026-03-30T03:03:17Z",
          "tier": "sonnet",
          "type": "multi-outcome",
          "avg_outcome_div": 0.46636666666666665,
          "max_outcome_div": 0.49800796812749004,
          "n_outcomes": 15
        }
      ],
      "avg_multi_div": 0.466
    },
    "which-company-will-have-the-best-ai-model-for-coding-on-march-31": {
      "n_predictions": 3,
      "history": [
        {
          "timestamp": "2026-03-29T01:27:58Z",
          "tier": "sonnet",
          "type": "multi-outcome",
          "avg_outcome_div": 0.3076838187702266,
          "max_outcome_div": 0.49029126213592233,
          "n_outcomes": 15
        },
        {
          "timestamp": "2026-03-29T03:02:03Z",
          "tier": "sonnet",
          "type": "multi-outcome",
          "avg_outcome_div": 0.3029709401709401,
          "max_outcome_div": 0.49240265906932573,
          "n_outcomes": 15
        },
        {
          "timestamp": "2026-03-30T03:03:17Z",
          "tier": "sonnet",
          "type": "multi-outcome",
          "avg_outcome_div": 0.31727366818873676,
          "max_outcome_div": 0.4817351598173516,
          "n_outcomes": 15
        }
      ],
      "avg_multi_div": 0.309
    },
    "will-the-us-confirm-that-aliens-exist-before-2027": {
      "n_predictions": 7,
      "history": [
        {
          "timestamp": "2026-03-30T03:03:17Z",
          "tier": "opus",
          "type": "multi-outcome",
          "avg_outcome_div": 0.41524999999999995,
          "max_outcome_div": 0.8106097560975609,
          "n_outcomes": 2
        },
        {
          "timestamp": "2026-03-31T02:54:04Z",
          "tier": "opus",
          "type": "multi-outcome",
          "avg_outcome_div": 0.41675,
          "max_outcome_div": 0.8267355371900826,
          "n_outcomes": 2
        },
        {
          "timestamp": "2026-04-02T02:53:10Z",
          "tier": "opus",
          "type": "multi-outcome",
          "avg_outcome_div": 0.422,
          "max_outcome_div": 0.835,
          "n_outcomes": 2
        },
        {
          "timestamp": "2026-04-03T02:55:31Z",
          "tier": "opus",
          "type": "multi-outcome",
          "avg_outcome_div": 0.413,
          "max_outcome_div": 0.758076923076923,
          "n_outcomes": 2
        },
        {
          "timestamp": "2026-04-04T02:44:25Z",
          "tier": "opus",
          "type": "multi-outcome",
          "avg_outcome_div": 0.413,
          "max_outcome_div": 0.7873809523809523,
          "n_outcomes": 2
        }
      ],
      "avg_multi_div": 0.416
    },
    "gta-6-launch-postponed-again": {
      "n_predictions": 7,
      "history": [
        {
          "timestamp": "2026-03-30T03:03:17Z",
          "tier": "haiku",
          "type": "binary",
          "prediction": 0.24,
          "market_price": 0.275,
          "signed_error": -0.03500000000000003
        },
        {
          "timestamp": "2026-03-31T02:54:04Z",
          "tier": "haiku",
          "type": "binary",
          "prediction": 0.26,
          "market_price": 0.27,
          "signed_error": -0.010000000000000009
        },
        {
          "timestamp": "2026-04-02T02:53:10Z",
          "tier": "haiku",
          "type": "binary",
          "prediction": 0.24,
          "market_price": 0.275,
          "signed_error": -0.03500000000000003
        },
        {
          "timestamp": "2026-04-03T02:55:31Z",
          "tier": "sonnet",
          "type": "binary",
          "prediction": 0.37,
          "market_price": 0.31,
          "signed_error": 0.06
        },
        {
          "timestamp": "2026-04-04T02:44:25Z",
          "tier": "sonnet",
          "type": "binary",
          "prediction": 0.35,
          "market_price": 0.33,
          "signed_error": 0.019999999999999962
        }
      ],
      "avg_signed_error": 0.001,
      "avg_abs_error": 0.027,
      "bias": "neutral"
    },
    "will-gas-hit-by-end-of-march": {
      "n_predictions": 2,
      "history": [
        {
          "timestamp": "2026-03-29T13:14:30Z",
          "tier": "opus",
          "type": "multi-outcome",
          "avg_outcome_div": 0.31024999999999997,
          "max_outcome_div": 0.7888675623800383,
          "n_outcomes": 12
        },
        {
          "timestamp": "2026-03-30T13:52:42Z",
          "tier": "opus",
          "type": "multi-outcome",
          "avg_outcome_div": 0.29641666666666666,
          "max_outcome_div": 0.7848518111964874,
          "n_outcomes": 12
        }
      ],
      "avg_multi_div": 0.303
    },
    "survivor-50-winner": {
      "n_predictions": 1,
      "history": [
        {
          "timestamp": "2026-03-30T03:03:17Z",
          "tier": "sonnet",
          "type": "multi-outcome",
          "avg_outcome_div": 0.4569999999999999,
          "max_outcome_div": 0.4854368932038835,
          "n_outcomes": 15
        }
      ],
      "avg_multi_div": 0.457
    }
  },
  "per_domain": {
    "geopolitics": {
      "n_predictions": 84,
      "avg_signed_error": -0.011,
      "avg_abs_error": 0.029,
      "bias": "neutral",
      "avg_multi_div": 0.252
    },
    "economics": {
      "n_predictions": 58,
      "avg_signed_error": -0.003,
      "avg_abs_error": 0.02,
      "bias": "neutral",
      "avg_multi_div": 0.232
    },
    "politics": {
      "n_predictions": 56,
      "avg_multi_div": 0.382
    },
    "sports": {
      "n_predictions": 14,
      "avg_multi_div": 0.173
    },
    "tech": {
      "n_predictions": 13,
      "avg_multi_div": 0.403
    },
    "entertainment": {
      "n_predictions": 8,
      "avg_signed_error": 0.001,
      "avg_abs_error": 0.027,
      "bias": "neutral",
      "avg_multi_div": 0.457
    }
  }
}