{
  "fetched_at": "2026-05-09T17:01:13Z",
  "source": "National Weather Service API (weather.gov)",
  "cities": {
    "nyc": {
      "label": "New York City",
      "relevant_to": [
        "nyc_temp"
      ],
      "today_high": 66,
      "today_high_unit": "F",
      "today_forecast": "Showers And Thunderstorms",
      "today_detail": "Rain showers likely before 2pm, then showers and thunderstorms. Cloudy. High near 66, with temperatures falling to around 59 in the afternoon. South wind 7 to 12 mph. Chance of precipitation is 100%. New rainfall amounts between a quarter and half of an inch possible.",
      "wind": "7 to 12 mph",
      "wind_direction": "S",
      "tonight_low": 53,
      "tonight_forecast": "Chance Showers And Thunderstorms then Areas Of Fog",
      "hourly": [
        {
          "hour": "2026-05-09T12:00:00-04:00",
          "temp": 63,
          "unit": "F",
          "short": "Rain Showers Likely"
        },
        {
          "hour": "2026-05-09T13:00:00-04:00",
          "temp": 62,
          "unit": "F",
          "short": "Rain Showers Likely"
        },
        {
          "hour": "2026-05-09T14:00:00-04:00",
          "temp": 61,
          "unit": "F",
          "short": "Showers And Thunderstorms"
        },
        {
          "hour": "2026-05-09T15:00:00-04:00",
          "temp": 60,
          "unit": "F",
          "short": "Showers And Thunderstorms"
        },
        {
          "hour": "2026-05-09T16:00:00-04:00",
          "temp": 59,
          "unit": "F",
          "short": "Showers And Thunderstorms"
        },
        {
          "hour": "2026-05-09T17:00:00-04:00",
          "temp": 59,
          "unit": "F",
          "short": "Showers And Thunderstorms"
        },
        {
          "hour": "2026-05-09T18:00:00-04:00",
          "temp": 59,
          "unit": "F",
          "short": "Chance Showers And Thunderstorms"
        },
        {
          "hour": "2026-05-09T19:00:00-04:00",
          "temp": 59,
          "unit": "F",
          "short": "Chance Showers And Thunderstorms"
        },
        {
          "hour": "2026-05-09T20:00:00-04:00",
          "temp": 58,
          "unit": "F",
          "short": "Partly Cloudy"
        },
        {
          "hour": "2026-05-09T21:00:00-04:00",
          "temp": 57,
          "unit": "F",
          "short": "Partly Cloudy"
        },
        {
          "hour": "2026-05-09T22:00:00-04:00",
          "temp": 57,
          "unit": "F",
          "short": "Patchy Fog"
        },
        {
          "hour": "2026-05-09T23:00:00-04:00",
          "temp": 57,
          "unit": "F",
          "short": "Patchy Fog"
        }
      ],
      "peak_temp": 63,
      "peak_hour": "2026-05-09T12:00:00-04:00"
    },
    "miami": {
      "label": "Miami",
      "relevant_to": [
        "miami_temp"
      ],
      "today_high": 96,
      "today_high_unit": "F",
      "today_forecast": "Sunny",
      "today_detail": "Sunny, with a high near 96. Heat index values as high as 100. Southwest wind around 7 mph.",
      "wind": "7 mph",
      "wind_direction": "SW",
      "tonight_low": 71,
      "tonight_forecast": "Partly Cloudy",
      "hourly": [
        {
          "hour": "2026-05-09T13:00:00-04:00",
          "temp": 93,
          "unit": "F",
          "short": "Sunny"
        },
        {
          "hour": "2026-05-09T14:00:00-04:00",
          "temp": 94,
          "unit": "F",
          "short": "Sunny"
        },
        {
          "hour": "2026-05-09T15:00:00-04:00",
          "temp": 94,
          "unit": "F",
          "short": "Sunny"
        },
        {
          "hour": "2026-05-09T16:00:00-04:00",
          "temp": 95,
          "unit": "F",
          "short": "Sunny"
        },
        {
          "hour": "2026-05-09T17:00:00-04:00",
          "temp": 94,
          "unit": "F",
          "short": "Sunny"
        },
        {
          "hour": "2026-05-09T18:00:00-04:00",
          "temp": 93,
          "unit": "F",
          "short": "Mostly Clear"
        },
        {
          "hour": "2026-05-09T19:00:00-04:00",
          "temp": 90,
          "unit": "F",
          "short": "Mostly Clear"
        },
        {
          "hour": "2026-05-09T20:00:00-04:00",
          "temp": 84,
          "unit": "F",
          "short": "Partly Cloudy"
        },
        {
          "hour": "2026-05-09T21:00:00-04:00",
          "temp": 81,
          "unit": "F",
          "short": "Partly Cloudy"
        },
        {
          "hour": "2026-05-09T22:00:00-04:00",
          "temp": 78,
          "unit": "F",
          "short": "Partly Cloudy"
        },
        {
          "hour": "2026-05-09T23:00:00-04:00",
          "temp": 77,
          "unit": "F",
          "short": "Partly Cloudy"
        }
      ],
      "peak_temp": 95,
      "peak_hour": "2026-05-09T16:00:00-04:00"
    }
  }
}