{
  "fetched_at": "2026-04-08T09:09:58Z",
  "source": "National Weather Service API (weather.gov)",
  "cities": {
    "nyc": {
      "label": "New York City",
      "relevant_to": [
        "nyc_temp"
      ],
      "today_high": 50,
      "today_high_unit": "F",
      "today_forecast": "Sunny",
      "today_detail": "Sunny. High near 50, with temperatures falling to around 47 in the afternoon. Wind chill values as low as 20. East wind 5 to 12 mph.",
      "wind": "5 to 12 mph",
      "wind_direction": "E",
      "tonight_low": 35,
      "tonight_forecast": "Mostly Clear then Areas Of Frost",
      "hourly": [
        {
          "hour": "2026-04-08T05:00:00-04:00",
          "temp": 30,
          "unit": "F",
          "short": "Clear"
        },
        {
          "hour": "2026-04-08T06:00:00-04:00",
          "temp": 30,
          "unit": "F",
          "short": "Sunny"
        },
        {
          "hour": "2026-04-08T07:00:00-04:00",
          "temp": 31,
          "unit": "F",
          "short": "Sunny"
        },
        {
          "hour": "2026-04-08T08:00:00-04:00",
          "temp": 32,
          "unit": "F",
          "short": "Sunny"
        },
        {
          "hour": "2026-04-08T09:00:00-04:00",
          "temp": 35,
          "unit": "F",
          "short": "Sunny"
        },
        {
          "hour": "2026-04-08T10:00:00-04:00",
          "temp": 38,
          "unit": "F",
          "short": "Sunny"
        },
        {
          "hour": "2026-04-08T11:00:00-04:00",
          "temp": 42,
          "unit": "F",
          "short": "Sunny"
        },
        {
          "hour": "2026-04-08T12:00:00-04:00",
          "temp": 45,
          "unit": "F",
          "short": "Sunny"
        },
        {
          "hour": "2026-04-08T13:00:00-04:00",
          "temp": 48,
          "unit": "F",
          "short": "Sunny"
        },
        {
          "hour": "2026-04-08T14:00:00-04:00",
          "temp": 50,
          "unit": "F",
          "short": "Sunny"
        },
        {
          "hour": "2026-04-08T15:00:00-04:00",
          "temp": 50,
          "unit": "F",
          "short": "Sunny"
        },
        {
          "hour": "2026-04-08T16:00:00-04:00",
          "temp": 49,
          "unit": "F",
          "short": "Sunny"
        },
        {
          "hour": "2026-04-08T17:00:00-04:00",
          "temp": 47,
          "unit": "F",
          "short": "Sunny"
        },
        {
          "hour": "2026-04-08T18:00:00-04:00",
          "temp": 45,
          "unit": "F",
          "short": "Clear"
        },
        {
          "hour": "2026-04-08T19:00:00-04:00",
          "temp": 43,
          "unit": "F",
          "short": "Clear"
        },
        {
          "hour": "2026-04-08T20:00:00-04:00",
          "temp": 41,
          "unit": "F",
          "short": "Clear"
        },
        {
          "hour": "2026-04-08T21:00:00-04:00",
          "temp": 40,
          "unit": "F",
          "short": "Clear"
        },
        {
          "hour": "2026-04-08T22:00:00-04:00",
          "temp": 39,
          "unit": "F",
          "short": "Clear"
        },
        {
          "hour": "2026-04-08T23:00:00-04:00",
          "temp": 39,
          "unit": "F",
          "short": "Clear"
        }
      ],
      "peak_temp": 50,
      "peak_hour": "2026-04-08T14:00:00-04:00"
    },
    "miami": {
      "label": "Miami",
      "relevant_to": [
        "miami_temp"
      ],
      "today_high": 80,
      "today_high_unit": "F",
      "today_forecast": "Showers And Thunderstorms Likely",
      "today_detail": "A slight chance of rain showers between 9am and 11am, then showers and thunderstorms likely between 11am and 5pm, then showers and thunderstorms likely. Partly sunny. High near 80, with temperatures falling to around 76 in the afternoon. Northeast wind 5 to 9 mph, with gusts as high as 20 mph. Chance of precipitation is 60%. New rainfall amounts between a tenth and quarter of an inch possible.",
      "wind": "5 to 9 mph",
      "wind_direction": "NE",
      "tonight_low": 62,
      "tonight_forecast": "Showers And Thunderstorms Likely",
      "hourly": [
        {
          "hour": "2026-04-08T04:00:00-04:00",
          "temp": 64,
          "unit": "F",
          "short": "Mostly Cloudy"
        },
        {
          "hour": "2026-04-08T05:00:00-04:00",
          "temp": 64,
          "unit": "F",
          "short": "Mostly Cloudy"
        },
        {
          "hour": "2026-04-08T06:00:00-04:00",
          "temp": 64,
          "unit": "F",
          "short": "Partly Sunny"
        },
        {
          "hour": "2026-04-08T07:00:00-04:00",
          "temp": 63,
          "unit": "F",
          "short": "Mostly Sunny"
        },
        {
          "hour": "2026-04-08T08:00:00-04:00",
          "temp": 64,
          "unit": "F",
          "short": "Mostly Sunny"
        },
        {
          "hour": "2026-04-08T09:00:00-04:00",
          "temp": 68,
          "unit": "F",
          "short": "Slight Chance Rain Showers"
        },
        {
          "hour": "2026-04-08T10:00:00-04:00",
          "temp": 72,
          "unit": "F",
          "short": "Slight Chance Rain Showers"
        },
        {
          "hour": "2026-04-08T11:00:00-04:00",
          "temp": 75,
          "unit": "F",
          "short": "Chance Showers And Thunderstorms"
        },
        {
          "hour": "2026-04-08T12:00:00-04:00",
          "temp": 76,
          "unit": "F",
          "short": "Chance Showers And Thunderstorms"
        },
        {
          "hour": "2026-04-08T13:00:00-04:00",
          "temp": 77,
          "unit": "F",
          "short": "Chance Showers And Thunderstorms"
        },
        {
          "hour": "2026-04-08T14:00:00-04:00",
          "temp": 78,
          "unit": "F",
          "short": "Showers And Thunderstorms Likely"
        },
        {
          "hour": "2026-04-08T15:00:00-04:00",
          "temp": 78,
          "unit": "F",
          "short": "Showers And Thunderstorms Likely"
        },
        {
          "hour": "2026-04-08T16:00:00-04:00",
          "temp": 78,
          "unit": "F",
          "short": "Showers And Thunderstorms Likely"
        },
        {
          "hour": "2026-04-08T17:00:00-04:00",
          "temp": 76,
          "unit": "F",
          "short": "Showers And Thunderstorms Likely"
        },
        {
          "hour": "2026-04-08T18:00:00-04:00",
          "temp": 75,
          "unit": "F",
          "short": "Showers And Thunderstorms Likely"
        },
        {
          "hour": "2026-04-08T19:00:00-04:00",
          "temp": 73,
          "unit": "F",
          "short": "Chance Showers And Thunderstorms"
        },
        {
          "hour": "2026-04-08T20:00:00-04:00",
          "temp": 69,
          "unit": "F",
          "short": "Chance Showers And Thunderstorms"
        },
        {
          "hour": "2026-04-08T21:00:00-04:00",
          "temp": 69,
          "unit": "F",
          "short": "Chance Showers And Thunderstorms"
        },
        {
          "hour": "2026-04-08T22:00:00-04:00",
          "temp": 67,
          "unit": "F",
          "short": "Chance Showers And Thunderstorms"
        },
        {
          "hour": "2026-04-08T23:00:00-04:00",
          "temp": 67,
          "unit": "F",
          "short": "Chance Showers And Thunderstorms"
        }
      ],
      "peak_temp": 78,
      "peak_hour": "2026-04-08T14:00:00-04:00"
    }
  }
}