{
  "timestamp": "2026-03-15T16:05:35Z",
  "market_prices": {
    "regime_fall": {
      "current": 0.295,
      "previous": 0.285,
      "change_4h": 0.01,
      "change_24h": 0.03,
      "history_24h": [
        {
          "t": 1773518726,
          "p": 0.265
        },
        {
          "t": 1773533149,
          "p": 0.265
        },
        {
          "t": 1773547535,
          "p": 0.265
        },
        {
          "t": 1773561935,
          "p": 0.295
        },
        {
          "t": 1773576333,
          "p": 0.285
        },
        {
          "t": 1773590735,
          "p": 0.295
        }
      ]
    }
  },
  "fresh_facts": [
    {
      "claim": "Approximately 2,200-2,500 US Marines from a Marine Expeditionary Unit aboard three Navy amphibious ships, including USS Tripoli, were ordered to the Middle East region by US Central Command.",
      "source": "PBS NewsHour, LiveNOW FOX, ABC News",
      "source_category": "us_prestige",
      "indicator_category": "military_pressure",
      "market": "regime_fall",
      "time": "2026-03-15T00:00:00Z",
      "confidence": "high"
    },
    {
      "claim": "US military strikes hit 90 military targets on Karak Island, Iran's main oil export hub, following threats of retaliation against energy infrastructure.",
      "source": "ABC News, PBS NewsHour",
      "source_category": "us_prestige",
      "indicator_category": "military_pressure",
      "market": "regime_fall",
      "time": "2026-03-15T00:00:00Z",
      "confidence": "high"
    },
    {
      "claim": "Iran responded to US strikes with drone attacks on UAE's Fujairah oil hub, suspending operations, and a missile attack on a US air base in southern Turkey.",
      "source": "ABC News, PBS NewsHour",
      "source_category": "us_prestige",
      "indicator_category": "military_pressure",
      "market": "regime_fall",
      "time": "2026-03-15T00:00:00Z",
      "confidence": "high"
    },
    {
      "claim": "US strikes in Iran have exceeded 15,000 targets over approximately two weeks of military operations.",
      "source": "PBS NewsHour, ABC News",
      "source_category": "us_prestige",
      "indicator_category": "military_pressure",
      "market": "regime_fall",
      "time": "2026-03-15T00:00:00Z",
      "confidence": "high"
    },
    {
      "claim": "Iran threatened to mine the Strait of Hormuz with hundreds of small boats; CENTCOM destroyed over a dozen Iranian mine-laying ships in response.",
      "source": "PBS NewsHour, ABC News",
      "source_category": "us_prestige",
      "indicator_category": "military_pressure",
      "market": "regime_fall",
      "time": "2026-03-15T00:00:00Z",
      "confidence": "high"
    },
    {
      "claim": "Over 50,000 US troops were already deployed in the region prior to the additional Marine deployment ordered by CENTCOM.",
      "source": "LiveNOW FOX, PBS NewsHour",
      "source_category": "us_prestige",
      "indicator_category": "military_pressure",
      "market": "regime_fall",
      "time": "2026-03-15T00:00:00Z",
      "confidence": "high"
    },
    {
      "claim": "President Trump rejected fresh ceasefire efforts and prioritized military pressure over negotiations on March 14.",
      "source": "PBS NewsHour",
      "source_category": "us_prestige",
      "indicator_category": "diplomatic_signals",
      "market": "regime_fall",
      "time": "2026-03-14T00:00:00Z",
      "confidence": "high"
    },
    {
      "claim": "Iranian armed forces spokesman Abolfazl Shekarchi warned neighboring countries against trusting US 'hollow power' on March 14.",
      "source": "PBS NewsHour",
      "source_category": "government_official",
      "indicator_category": "diplomatic_signals",
      "market": "regime_fall",
      "time": "2026-03-14T00:00:00Z",
      "confidence": "high"
    },
    {
      "claim": "Iranian officials denied leadership tensions on March 14, with the foreign minister affirming stable relations between government institutions and the Supreme Leader's office.",
      "source": "PBS NewsHour",
      "source_category": "government_official",
      "indicator_category": "succession_dynamics",
      "market": "regime_fall",
      "time": "2026-03-14T00:00:00Z",
      "confidence": "medium"
    },
    {
      "claim": "Mojtaba Khamenei, appointed as Supreme Leader after March 5, issued his first statement on March 12.",
      "source": "PBS NewsHour, LiveNOW FOX, ABC News",
      "source_category": "us_prestige",
      "indicator_category": "succession_dynamics",
      "market": "regime_fall",
      "time": "2026-03-12T00:00:00Z",
      "confidence": "high"
    },
    {
      "claim": "A nationwide internet blackout in Iran exceeded 13 days as of March 13, enabling preparations for mass killings and purges under 'war conditions'.",
      "source": "PBS NewsHour",
      "source_category": "us_prestige",
      "indicator_category": "internal_stability",
      "market": "regime_fall",
      "time": "2026-03-13T00:00:00Z",
      "confidence": "medium"
    },
    {
      "claim": "Qatar, UAE, and Saudi Arabia reported intercepting Iranian missiles and drones over their territories on March 14, with evacuations in Doha.",
      "source": "PBS NewsHour",
      "source_category": "us_prestige",
      "indicator_category": "military_pressure",
      "market": "regime_fall",
      "time": "2026-03-14T00:00:00Z",
      "confidence": "high"
    },
    {
      "claim": "Casualties from US strikes included 15 deaths in Isfahan and a Basij commander in Tehran on March 14.",
      "source": "ABC News",
      "source_category": "us_prestige",
      "indicator_category": "military_pressure",
      "market": "regime_fall",
      "time": "2026-03-14T00:00:00Z",
      "confidence": "medium"
    },
    {
      "claim": "Iran attacked the US embassy in Baghdad in response to US strikes on military targets.",
      "source": "ABC News, PBS NewsHour",
      "source_category": "us_prestige",
      "indicator_category": "military_pressure",
      "market": "regime_fall",
      "time": "2026-03-15T00:00:00Z",
      "confidence": "high"
    },
    {
      "claim": "NCRI's Maryam Rajavi announced a provisional government framework on February 28 as a democratic alternative post-regime collapse.",
      "source": "PBS NewsHour",
      "source_category": "us_prestige",
      "indicator_category": "international_response",
      "market": "regime_fall",
      "time": "2026-02-28T00:00:00Z",
      "confidence": "medium"
    },
    {
      "claim": "Iranian Resistance rallies in Berlin endorsed NCRI plans as of March 11.",
      "source": "PBS NewsHour",
      "source_category": "us_prestige",
      "indicator_category": "international_response",
      "market": "regime_fall",
      "time": "2026-03-11T00:00:00Z",
      "confidence": "medium"
    },
    {
      "claim": "A midday strike killed at least one person during an Iranian rally chanting 'Death to America/Israel' with flag burnings in solidarity with Palestinians.",
      "source": "PBS NewsHour",
      "source_category": "us_prestige",
      "indicator_category": "military_pressure",
      "market": "regime_fall",
      "time": "2026-03-13T00:00:00Z",
      "confidence": "medium"
    },
    {
      "claim": "President Trump claimed Iran is 'totally defeated' but seeking an unacceptable deal.",
      "source": "ABC News, PBS NewsHour",
      "source_category": "us_prestige",
      "indicator_category": "diplomatic_signals",
      "market": "regime_fall",
      "time": "2026-03-15T00:00:00Z",
      "confidence": "high"
    },
    {
      "claim": "Reports indicate possible Russian aid to Iran amid the ongoing US-Iran military conflict.",
      "source": "ABC News",
      "source_category": "us_prestige",
      "indicator_category": "international_response",
      "market": "regime_fall",
      "time": "2026-03-15T00:00:00Z",
      "confidence": "low"
    },
    {
      "claim": "Iran closed the Strait of Hormuz via missile and drone attacks in response to US military operations.",
      "source": "PBS NewsHour, LiveNOW FOX, ABC News",
      "source_category": "us_prestige",
      "indicator_category": "military_pressure",
      "market": "regime_fall",
      "time": "2026-03-15T00:00:00Z",
      "confidence": "high"
    }
  ],
  "state": {
    "last_updated": "2026-03-15T00:00:00Z",
    "markets": {
      "regime_fall": {
        "current_status": "Unprecedented escalation with US conducting 15,000+ strikes over two weeks, destroying Iranian military infrastructure including oil export facilities and mine-laying capabilities, while Iran responds with regional missile and drone attacks on UAE, Turkey, and US embassy in Baghdad; Mojtaba Khamenei consolidates power under 13+ day internet blackout as regime manages simultaneous external military devastation and internal security operations.",
        "last_major_event": "US military operations expanded to over 15,000 strikes targeting Iranian military infrastructure including Karak Island oil hub and mine-laying ships, while Iran launched coordinated attacks on UAE Fujairah oil hub, US air base in Turkey, and US embassy in Baghdad, with 50,000+ US troops in region supplemented by additional 2,200-2,500 Marines.",
        "last_major_event_time": "2026-03-15T00:00:00Z",
        "military_pressure": "critical",
        "internal_stability": "critical",
        "succession_dynamics": "high",
        "diplomatic_signals": "critical",
        "economic_collapse": "critical",
        "international_response": "high"
      }
    }
  },
  "price_history_path": "price_history/prices.csv"
}